qtradingview/__init__.py
qtradingview/alarms/__init__.py
qtradingview/alarms/dialog.py
qtradingview/alarms/dock.py
qtradingview/alarms/models.py
qtradingview/alarms/widgets.py
qtradingview/base/__init__.py
qtradingview/base/dialog_about.py
qtradingview/base/dialog_config.py
qtradingview/base/mainwindow.py
qtradingview/base/widgets.py
qtradingview/context.py
qtradingview/debug/__init__.py
qtradingview/debug/dock.py
qtradingview/i18n/en_EN.qm
qtradingview/i18n/en_EN.ts
qtradingview/i18n/es_ES.qm
qtradingview/i18n/es_ES.ts
qtradingview/icons/actions/alarms.svg
qtradingview/icons/actions/debug.svg
qtradingview/icons/actions/markets.svg
qtradingview/icons/actions/portfolio.png
qtradingview/icons/actions/salir.svg
qtradingview/icons/actions/screen.svg
qtradingview/icons/actions/settings.svg
qtradingview/icons/actions/update.svg
qtradingview/icons/base/logo.svg
qtradingview/icons/base/margin.svg
qtradingview/icons/base/notify.wav
qtradingview/icons/base/splash.png
qtradingview/icons/base/star.svg
qtradingview/icons/base/unstar.svg
qtradingview/icons/base/voidstar.svg
qtradingview/icons/exchanges/binance.png
qtradingview/icons/exchanges/bitbay.png
qtradingview/icons/exchanges/bitfinex.png
qtradingview/icons/exchanges/bithumb.png
qtradingview/icons/exchanges/bitso.png
qtradingview/icons/exchanges/bitstamp.png
qtradingview/icons/exchanges/bittrex.png
qtradingview/icons/exchanges/coinbase.png
qtradingview/icons/exchanges/gemini.png
qtradingview/icons/exchanges/hitbtc.png
qtradingview/icons/exchanges/kraken.png
qtradingview/icons/exchanges/kucoin.png
qtradingview/icons/exchanges/okcoin.png
qtradingview/icons/exchanges/poloniex.png
qtradingview/icons/exchanges/therock.png
qtradingview/icons/iconos.qrc
qtradingview/icons/logo.ico
qtradingview/icons/logo.png
qtradingview/icons/logo.svg
qtradingview/icons/screenshots/demo.png
qtradingview/icons/splash.png
qtradingview/main.py
qtradingview/markets/__init__.py
qtradingview/markets/dock.py
qtradingview/markets/updater.py
qtradingview-0.19.6.dist-info/entry_points.txt
qtradingview-0.19.6.dist-info/LICENSE
qtradingview-0.19.6.dist-info/WHEEL
qtradingview-0.19.6.dist-info/METADATA
qtradingview-0.19.6.dist-info/RECORD
