Metadata-Version: 2.1
Name: qtradingview
Version: 0.19.6
Summary: PyQt App for TradingView
Author: katmai
Author-email: katmai.mobil@gmail.com
Requires-Python: >=3.7,<4.0
Classifier: Programming Language :: Python :: 3
Classifier: Programming Language :: Python :: 3.7
Classifier: Programming Language :: Python :: 3.8
Classifier: Programming Language :: Python :: 3.9
Requires-Dist: PyQtWebEngine (>=5.15.1,<6.0.0)
Requires-Dist: beautifulsoup4 (>=4.9.3,<5.0.0)
Requires-Dist: cached-property (>=1.5.2,<2.0.0)
Requires-Dist: ccxt (>=1.37.52,<2.0.0)
Requires-Dist: coloredlogs (>=14.0,<15.0)
Requires-Dist: docopt (>=0.6.2,<0.7.0)
Requires-Dist: html5lib (>=1.1,<2.0)
Requires-Dist: peewee (>=3.14.0,<4.0.0)
Requires-Dist: pyqt5-notificator (>=1.0.12,<2.0.0)
Requires-Dist: toml (>=0.10.2,<0.11.0)
